bitcoin_safe_lib/__init__.py
bitcoin_safe_lib/async_tools/loop_in_thread.py
bitcoin_safe_lib/caching.py
bitcoin_safe_lib/gui/qt/i18n.py
bitcoin_safe_lib/gui/qt/icons.py
bitcoin_safe_lib/gui/qt/satoshis.py
bitcoin_safe_lib/gui/qt/signal_tracker.py
bitcoin_safe_lib/gui/qt/util.py
bitcoin_safe_lib/tx_util.py
bitcoin_safe_lib/util.py
bitcoin_safe_lib/util_os.py
bitcoin_safe_lib-0.2.7.dist-info/LICENSE
bitcoin_safe_lib-0.2.7.dist-info/METADATA
bitcoin_safe_lib-0.2.7.dist-info/WHEEL
bitcoin_safe_lib-0.2.7.dist-info/RECORD
