Metadata-Version: 2.3
Name: bitcoin-safe-lib
Version: 0.2.7
Summary: Python tools and library
License: GPL-3.0
Author: andreasgriffin
Author-email: andreasgriffin@proton.me
Requires-Python: >=3.10,<3.13
Classifier: License :: OSI Approved :: GNU General Public License v3 (GPLv3)
Classifier: Programming Language :: Python :: 3
Classifier: Programming Language :: Python :: 3.10
Classifier: Programming Language :: Python :: 3.11
Classifier: Programming Language :: Python :: 3.12
Requires-Dist: bdkpython (>=1.2.0,<2.0.0)
Requires-Dist: numpy (==2.2.1)
Requires-Dist: pyqt6 (>=6.9.0,<7.0.0)
Project-URL: Homepage, https://github.com/andreasgriffin
